[{"id":16,"name":"ケイ・エム・プロデュース","fanza_id":"40071","logo_url":null,"work_count":0,"created_at":"2026-02-02 13:30:33"},{"id":31,"name":"ちんちんVR","fanza_id":"40388","logo_url":null,"work_count":0,"created_at":"2026-02-02 15:03:08"},{"id":30,"name":"CASANOVA","fanza_id":"46483","logo_url":null,"work_count":0,"created_at":"2026-02-02 15:03:07"},{"id":29,"name":"E-BODY","fanza_id":"5032","logo_url":null,"work_count":0,"created_at":"2026-02-02 15:03:07"},{"id":28,"name":"ROOKIE","fanza_id":"5665","logo_url":null,"work_count":0,"created_at":"2026-02-02 15:03:07"},{"id":27,"name":"V＆R PRODUCE","fanza_id":"46232","logo_url":null,"work_count":0,"created_at":"2026-02-02 15:03:06"},{"id":26,"name":"アタッカーズ","fanza_id":"1227","logo_url":null,"work_count":0,"created_at":"2026-02-02 15:03:06"},{"id":25,"name":"SPICY VR","fanza_id":"301447","logo_url":null,"work_count":0,"created_at":"2026-02-02 15:03:05"},{"id":24,"name":"スクープ","fanza_id":"45837","logo_url":null,"work_count":0,"created_at":"2026-02-02 15:03:05"},{"id":23,"name":"S-Cute","fanza_id":"45414","logo_url":null,"work_count":0,"created_at":"2026-02-02 15:03:04"},{"id":22,"name":"KMPVR-bibi-","fanza_id":"40404","logo_url":null,"work_count":0,"created_at":"2026-02-02 15:03:03"},{"id":21,"name":"ブイワンVR","fanza_id":"46496","logo_url":null,"work_count":0,"created_at":"2026-02-02 15:03:03"},{"id":20,"name":"DOC","fanza_id":"6716","logo_url":null,"work_count":0,"created_at":"2026-02-02 15:03:02"},{"id":19,"name":"TMA","fanza_id":"40041","logo_url":null,"work_count":0,"created_at":"2026-02-02 13:30:34"},{"id":18,"name":"unfinished","fanza_id":"45867","logo_url":null,"work_count":0,"created_at":"2026-02-02 13:30:33"},{"id":17,"name":"こあらVR","fanza_id":"46629","logo_url":null,"work_count":0,"created_at":"2026-02-02 13:30:33"},{"id":1,"name":"P-BOX VR","fanza_id":"40534","logo_url":null,"work_count":0,"created_at":"2026-02-02 13:30:32"},{"id":15,"name":"肉きゅんパラダイスVR","fanza_id":"300566","logo_url":null,"work_count":0,"created_at":"2026-02-02 13:30:33"},{"id":14,"name":"アリスJAPAN","fanza_id":"40039","logo_url":null,"work_count":0,"created_at":"2026-02-02 13:30:32"},{"id":13,"name":"CRYSTAL VR","fanza_id":"46522","logo_url":null,"work_count":0,"created_at":"2026-02-02 13:30:32"},{"id":12,"name":"お夜食カンパニー","fanza_id":"6571","logo_url":null,"work_count":0,"created_at":"2026-02-02 13:30:32"},{"id":11,"name":"kawaii","fanza_id":"4469","logo_url":null,"work_count":0,"created_at":"2026-02-02 13:30:32"},{"id":10,"name":"FALENO","fanza_id":"40488","logo_url":null,"work_count":0,"created_at":"2026-02-02 13:30:32"},{"id":9,"name":"KMPVR-彩-","fanza_id":"46628","logo_url":null,"work_count":0,"created_at":"2026-02-02 13:30:32"},{"id":8,"name":"マドンナ","fanza_id":"2661","logo_url":null,"work_count":0,"created_at":"2026-02-02 13:30:32"},{"id":7,"name":"プレミアム","fanza_id":"3890","logo_url":null,"work_count":0,"created_at":"2026-02-02 13:30:32"},{"id":6,"name":"アイデアポケット","fanza_id":"1219","logo_url":null,"work_count":0,"created_at":"2026-02-02 13:30:32"},{"id":5,"name":"本中","fanza_id":"6304","logo_url":null,"work_count":0,"created_at":"2026-02-02 13:30:32"},{"id":4,"name":"SODクリエイト","fanza_id":"45276","logo_url":null,"work_count":0,"created_at":"2026-02-02 13:30:32"},{"id":3,"name":"エスワン ナンバーワンスタイル","fanza_id":"3152","logo_url":null,"work_count":0,"created_at":"2026-02-02 13:30:32"},{"id":2,"name":"ムーディーズ","fanza_id":"1509","logo_url":null,"work_count":0,"created_at":"2026-02-02 13:30:32"}]